{
  "stats": {
    "commits": 0,
    "pullRequests": 25,
    "issues": 25,
    "reviews": 11
  },
  "contributions": [
    {
      "title": "merged PR: undefined",
      "description": "Pull request",
      "date": "2026-05-03",
      "type": "pull_request"
    },
    {
      "title": "closed issue: Created Critical Security Issue in Security and quality",
      "description": "TYPE BUG ( SECURITY )\nContributor For Nsoc",
      "date": "2026-05-03",
      "url": "https://github.com/S3DFX-CYBER/GSoC-Org-Finder-/issues/171",
      "type": "issue"
    },
    {
      "title": "labeled issue: feat: AI-Powered Org Recommender for Personalized GSoC Suggestions",
      "description": "## ✨ Feature Description\nIntroduce an AI-powered recommendation system that suggests the most relevant GSoC organizations to users based on their prof",
      "date": "2026-05-03",
      "url": "https://github.com/S3DFX-CYBER/GSoC-Org-Finder-/issues/169",
      "type": "issue"
    },
    {
      "title": "labeled issue: Feature: Interactive Watchlist & Dynamic AI Insights",
      "description": "### 📌 Overview\n\nThe project currently includes a basic Watchlist system where bookmarks are saved using `localStorage`. However:\n\n* The Watchlist UI ",
      "date": "2026-05-03",
      "url": "https://github.com/S3DFX-CYBER/GSoC-Org-Finder-/issues/170",
      "type": "issue"
    },
    {
      "title": "labeled issue: Feature: Interactive Watchlist & Dynamic AI Insights",
      "description": "### 📌 Overview\n\nThe project currently includes a basic Watchlist system where bookmarks are saved using `localStorage`. However:\n\n* The Watchlist UI ",
      "date": "2026-05-03",
      "url": "https://github.com/S3DFX-CYBER/GSoC-Org-Finder-/issues/170",
      "type": "issue"
    },
    {
      "title": "assigned issue: Feature: Interactive Watchlist & Dynamic AI Insights",
      "description": "### 📌 Overview\n\nThe project currently includes a basic Watchlist system where bookmarks are saved using `localStorage`. However:\n\n* The Watchlist UI ",
      "date": "2026-05-03",
      "url": "https://github.com/S3DFX-CYBER/GSoC-Org-Finder-/issues/170",
      "type": "issue"
    },
    {
      "title": "labeled issue: Feature: Add a keyboard shortcuts help modal (press '?' to open)",
      "description": "## 🐣 Good First Issue\n\n### Summary\nThe app already supports keyboard navigation (`↑ ↓ ← →`, `Enter`, `C`, `Esc`) but users have no way to discover th",
      "date": "2026-05-03",
      "url": "https://github.com/S3DFX-CYBER/GSoC-Org-Finder-/issues/70",
      "type": "issue"
    },
    {
      "title": "unassigned issue: Feature: Add a keyboard shortcuts help modal (press '?' to open)",
      "description": "## 🐣 Good First Issue\n\n### Summary\nThe app already supports keyboard navigation (`↑ ↓ ← →`, `Enter`, `C`, `Esc`) but users have no way to discover th",
      "date": "2026-05-03",
      "url": "https://github.com/S3DFX-CYBER/GSoC-Org-Finder-/issues/70",
      "type": "issue"
    },
    {
      "title": "assigned issue: Feature: Add a keyboard shortcuts help modal (press '?' to open)",
      "description": "## 🐣 Good First Issue\n\n### Summary\nThe app already supports keyboard navigation (`↑ ↓ ← →`, `Enter`, `C`, `Esc`) but users have no way to discover th",
      "date": "2026-05-03",
      "url": "https://github.com/S3DFX-CYBER/GSoC-Org-Finder-/issues/70",
      "type": "issue"
    },
    {
      "title": "closed issue: UX: Add a friendly empty state when no organizations match the active filters",
      "description": "## 🐣 Good First Issue\n\n### Summary\nWhen a user applies filters or types a search term that matches zero organizations, the org grid currently just go",
      "date": "2026-05-03",
      "url": "https://github.com/S3DFX-CYBER/GSoC-Org-Finder-/issues/75",
      "type": "issue"
    },
    {
      "title": "Pushed commits to S3DFX-CYBER/GSoC-Org-Finder-",
      "description": "Code changes",
      "date": "2026-05-03",
      "url": "https://github.com/S3DFX-CYBER/GSoC-Org-Finder-",
      "type": "commit"
    },
    {
      "title": "labeled PR: undefined",
      "description": "Pull request",
      "date": "2026-05-03",
      "type": "pull_request"
    },
    {
      "title": "labeled PR: undefined",
      "description": "Pull request",
      "date": "2026-05-03",
      "type": "pull_request"
    },
    {
      "title": "Reviewed PR: undefined",
      "description": "Pull request review",
      "date": "2026-05-03",
      "type": "review"
    },
    {
      "title": "labeled PR: undefined",
      "description": "Pull request",
      "date": "2026-05-03",
      "type": "pull_request"
    },
    {
      "title": "labeled PR: undefined",
      "description": "Pull request",
      "date": "2026-05-03",
      "type": "pull_request"
    },
    {
      "title": "labeled PR: undefined",
      "description": "Pull request",
      "date": "2026-05-03",
      "type": "pull_request"
    },
    {
      "title": "labeled PR: undefined",
      "description": "Pull request",
      "date": "2026-05-03",
      "type": "pull_request"
    },
    {
      "title": "labeled PR: undefined",
      "description": "Pull request",
      "date": "2026-05-03",
      "type": "pull_request"
    },
    {
      "title": "labeled PR: undefined",
      "description": "Pull request",
      "date": "2026-05-03",
      "type": "pull_request"
    }
  ],
  "lastUpdated": "2026-05-04T01:56:07.523Z"
}